{"web":{"client_id":"98591157039-5t1inafmhqtpnnmbkvjnkf3trd91ape9.apps.googleusercontent.com","project_id":"remotemcp","auth_uri":"https://accounts.google.com/o/oauth2/auth","token_uri":"https://oauth2.googleapis.com/token","auth_provider_x509_cert_url":"https://www.googleapis.com/oauth2/v1/certs","client_secret":"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","redirect_uris":["https://flodesk-remote-mcp.chris-1bd.workers.dev/callback"],"javascript_origins":["https://flodesk-remote-mcp.chris-1bd.workers.dev"]}}